<?xml version='1.1' encoding='UTF-8'?>
<fingerprint>
  <timestamp>2020-11-11 15:42:55.899 UTC</timestamp>
  <original>
    <name>rescue-sumo_4.14.98_GA-next-internal</name>
    <number>95</number>
  </original>
  <md5sum>6a6923c72066d274deb9895b0bff1c8a</md5sum>
  <fileName>fitImage-tn-image-rescue-initramfs-edm-imx6-4.14.98-r1-20201111123616.bin</fileName>
  <usages>
    <entry>
      <string>rescue-sumo_4.14.98_GA-next-internal</string>
      <ranges>95</ranges>
    </entry>
  </usages>
  <facets/>
</fingerprint>