<?xml version='1.1' encoding='UTF-8'?>
<fingerprint>
  <timestamp>2020-10-09 14:10:15.258 UTC</timestamp>
  <original>
    <name>github_tn-kernel-4.14.98-arm64</name>
    <number>91</number>
  </original>
  <md5sum>f2295524833607fa2fa338ec5258c2ab</md5sum>
  <fileName>modules.tar</fileName>
  <usages>
    <entry>
      <string>rescue-buildroot-install-modules64-4.14.98</string>
      <ranges>95</ranges>
    </entry>
    <entry>
      <string>github_tn-kernel-4.14.98-arm64</string>
      <ranges>91</ranges>
    </entry>
  </usages>
  <facets/>
</fingerprint>