<?xml version='1.1' encoding='UTF-8'?>
<fingerprint>
  <timestamp>2018-12-06 10:45:15.874 UTC</timestamp>
  <original>
    <name>github_tn-kernel-4.1.15</name>
    <number>6</number>
  </original>
  <md5sum>768b9384fcc72cb978c3adfd0452c22e</md5sum>
  <fileName>imx6q-edm1-cf-pmic_fairy.dtb</fileName>
  <usages>
    <entry>
      <string>rescue-diskimage-4.1.15</string>
      <ranges>55-59</ranges>
    </entry>
    <entry>
      <string>github_tn-kernel-4.1.15</string>
      <ranges>6-7</ranges>
    </entry>
    <entry>
      <string>rescue-imximage-4.1.15</string>
      <ranges>32-36</ranges>
    </entry>
  </usages>
  <facets/>
</fingerprint>