<?xml version='1.1' encoding='UTF-8'?>
<fingerprint>
  <timestamp>2019-08-23 22:02:48.596 UTC</timestamp>
  <original>
    <name>github_tn-kernel-4.14.98-arm64</name>
    <number>14</number>
  </original>
  <md5sum>8e0755e00ed94519a7ed66d0ad36b604</md5sum>
  <fileName>imx8mq-edm-wizard-dcss-ili9881c.dtb</fileName>
  <usages>
    <entry>
      <string>rescue-diskimage-4.14.98-imx8mq</string>
      <ranges>49</ranges>
    </entry>
    <entry>
      <string>rescue-diskimage-4.14.98-imx8mq-edm</string>
      <ranges>35</ranges>
    </entry>
    <entry>
      <string>rescue-diskimage-4.14.98-imx8mm</string>
      <ranges>47</ranges>
    </entry>
    <entry>
      <string>rescue-diskimage-4.14.98-imx8mm-flex</string>
      <ranges>47</ranges>
    </entry>
  </usages>
  <facets/>
</fingerprint>