<?xml version='1.1' encoding='UTF-8'?>
<fingerprint>
  <timestamp>2021-02-03 02:29:27.42 UTC</timestamp>
  <original>
    <name>yocto-sumo_4.14.98_GA-virtualization-internal</name>
    <number>60</number>
  </original>
  <md5sum>05d7a354a5692cf5602d381b05c39526</md5sum>
  <fileName>tn-image-docker-os-pico-imx8mm-20210203014453.rootfs.wic</fileName>
  <usages>
    <entry>
      <string>yocto-sumo_4.14.98_GA-virtualization-internal</string>
      <ranges>60</ranges>
    </entry>
  </usages>
  <facets/>
</fingerprint>