<?xml version='1.1' encoding='UTF-8'?>
<fingerprint>
  <timestamp>2021-03-04 21:27:55.194 UTC</timestamp>
  <original>
    <name>rescue-sumo_4.14.98_GA-next-internal</name>
    <number>132</number>
  </original>
  <md5sum>1df21e9d9ffe9889b3f078e10d5c3349</md5sum>
  <fileName>tn-image-rescue-initramfs-pico-imx6ul-20210304143622.rootfs.cpio.xz</fileName>
  <usages>
    <entry>
      <string>rescue-sumo_4.14.98_GA-next-internal</string>
      <ranges>132</ranges>
    </entry>
  </usages>
  <facets/>
</fingerprint>