<?xml version='1.1' encoding='UTF-8'?>
<fingerprint>
  <timestamp>2021-03-04 21:27:46.897 UTC</timestamp>
  <original>
    <name>rescue-sumo_4.14.98_GA-next-internal</name>
    <number>132</number>
  </original>
  <md5sum>467a7c16d79686be76397537df2a00d0</md5sum>
  <fileName>tn-image-rescue-initramfs-pico-imx6-20210304123651.rootfs.cpio.xz</fileName>
  <usages>
    <entry>
      <string>rescue-sumo_4.14.98_GA-next-internal</string>
      <ranges>132</ranges>
    </entry>
  </usages>
  <facets/>
</fingerprint>