<?xml version='1.1' encoding='UTF-8'?>
<fingerprint>
  <timestamp>2020-07-10 09:04:35.386 UTC</timestamp>
  <original>
    <name>yocto-rocko_4.9.y_GA-build</name>
    <number>100</number>
  </original>
  <md5sum>7f7ae83a18612a41ad0f53269b297097</md5sum>
  <fileName>fsl-image-qt5-validation-imx-tep1-imx7-20200710081904.rootfs.sdcard.bz2</fileName>
  <usages>
    <entry>
      <string>yocto-rocko_4.9.y_GA-build</string>
      <ranges>100</ranges>
    </entry>
  </usages>
  <facets/>
</fingerprint>