<?xml version='1.1' encoding='UTF-8'?>
<fingerprint>
  <timestamp>2020-01-08 05:27:58.557 UTC</timestamp>
  <original>
    <name>android-pie_9_image-build-scripts</name>
    <number>100</number>
  </original>
  <md5sum>d920e832ce28867396a5371205e0df14</md5sum>
  <fileName>pico-imx8mm_pico-pi-imx8m_android-9.0.0-2.0.1_QCA9377_mipi-dsi-ili9881c-1280x720_20200107.img.xz</fileName>
  <usages>
    <entry>
      <string>android-pie_9_upload_image</string>
      <ranges>77</ranges>
    </entry>
  </usages>
  <facets/>
</fingerprint>